README.rst
setup.py
pymdict/__init__.py
pymdict/mongo_dict.py
pymdict/mongo_query_parser.py
pymdict.egg-info/PKG-INFO
pymdict.egg-info/SOURCES.txt
pymdict.egg-info/dependency_links.txt
pymdict.egg-info/not-zip-safe
pymdict.egg-info/requires.txt
pymdict.egg-info/top_level.txt
test/__init__.py
test/test_mongo_query_parser.py
test/test_pymdict.py