Metadata-Version: 1.1
Name: pymdict
Version: 0.0.4
Summary: Python Mongo-Dict, a dictionary-like class automatically stored in mongo, with query capabilities.
Home-page: http://github.com/ipazc/pymdict
Author: Iván de Paz Centeno
Author-email: ipazc@unileon.es
License: MIT
Keywords: pymdict mongo dict python query advanced fork pip package
Platform: UNKNOWN
Classifier: Environment :: Console
Classifier: Intended Audience :: Developers
Classifier: Intended Audience :: Education
Classifier: Intended Audience :: Science/Research
Classifier: Natural Language :: English
Classifier: Programming Language :: Python :: 3.4
Classifier: Programming Language :: Python :: 3.5
Classifier: Programming Language :: Python :: 3.6
Classifier: Programming Language :: Python :: 3.7
